yieldthought_agents/__init__.py
yieldthought_agents/github.py
yieldthought_agents/shell.py
yieldthought_agents/worker.py
yieldthought_agents/tasks/__init__.py
yieldthought_agents/tasks/functional_bringup.py
yieldthought_agents-0.1.0.dist-info/METADATA
yieldthought_agents-0.1.0.dist-info/WHEEL
yieldthought_agents-0.1.0.dist-info/entry_points.txt
yieldthought_agents-0.1.0.dist-info/top_level.txt
yieldthought_agents-0.1.0.dist-info/RECORD
