Metadata-Version: 2.4
Name: yieldthought-agents
Version: 0.1.0
Summary: Automation for TTNN model bringup.
Requires-Python: >=3.10
Requires-Dist: codexapi>=0.1.3
Provides-Extra: dev
Requires-Dist: pytest; extra == "dev"
